MANIFEST.in
Readme.rst
requirements.txt
setup.py
Puppet_Diamond.egg-info/PKG-INFO
Puppet_Diamond.egg-info/SOURCES.txt
Puppet_Diamond.egg-info/dependency_links.txt
Puppet_Diamond.egg-info/not-zip-safe
Puppet_Diamond.egg-info/requires.txt
Puppet_Diamond.egg-info/top_level.txt
bin/add_submodule.sh
bin/domo-apply.sh
bin/domo-new.sh
bin/domo-sync.sh
bin/domo-test.sh
bin/generate_sshd_keys.sh
bin/get_puppet_certs.py
bin/get_submodules.sh
puppet/domo.pp
puppet/functions.pp
puppet/site.pp
puppet_diamond/__init__.py
puppet_diamond/__meta__.py
skels/diamond-module/.mrbob.ini
skels/diamond-module/sslcert.sh.bob
skels/diamond-module/files/+application.name+.conf.bob
skels/diamond-module/files/nginx.conf.bob
skels/diamond-module/files/upstart.conf.bob
skels/diamond-module/files/ssh/config.bob
skels/diamond-module/files/ssh/id_rsa.bob
skels/diamond-module/files/ssh/known_hosts.bob
skels/diamond-module/manifests/init.pp.bob
skels/digitalocean-host/.mrbob.ini
skels/digitalocean-host/Vagrantfile.bob
skels/digitalocean-host/puppet/puppet.conf.bob
skels/digitalocean-host/puppet/puppet.list
skels/digitalocean-host/puppet/puppet_init.sh
skels/profile/+shortname+.pp.bob
skels/profile/.mrbob.ini
skels/puppet-diamond/.mrbob.ini
skels/puppet-diamond/.puppet-diamond.bob
skels/puppet-module/.mrbob.ini
skels/puppet-module/Readme.md.bob
skels/puppet-module/files/simple.conf
skels/puppet-module/manifests/init.pp.bob
skels/puppet-module/templates/default.conf.erb
skels/puppetmaster/.gitmodules.bob
skels/puppetmaster/.mrbob.ini
skels/puppetmaster/puppetmaster.sh
skels/puppetmaster/hosts/.gitignore
skels/puppetmaster/modules/core/.gitignore
skels/puppetmaster/modules/diamond/.gitignore
skels/puppetmaster/modules/puppet/.gitignore
skels/puppetmaster/profiles/.gitignore