Metadata-Version: 1.1
Name: Puppet-Diamond
Version: 0.2.5
Summary: Puppet-Diamond can manage an IT Enterprise consisting of many Linux servers.
Home-page: http://diamond-methods.org/puppet-diamond.html
Author: Ian Dennis Miller
Author-email: iandennismiller@gmail.com
License: MIT
Platform: UNKNOWN
Classifier: Development Status :: 4 - Beta
Classifier: Intended Audience :: Developers
Classifier: Intended Audience :: Information Technology
Classifier: Intended Audience :: Science/Research
Classifier: License :: OSI Approved :: MIT License
Classifier: Operating System :: POSIX
Classifier: Operating System :: MacOS :: MacOS X
Classifier: Programming Language :: Python :: 2.7
Classifier: Topic :: System :: Clustering
Classifier: Topic :: System :: Systems Administration
